loudml_py/__init__.py
loudml_py/_version.py
loudml_py/buckets.py
loudml_py/cli.py
loudml_py/client.py
loudml_py/connection_pool.py
loudml_py/errors.py
loudml_py/jobs.py
loudml_py/misc.py
loudml_py/models.py
loudml_py/nab.py
loudml_py/randevents.py
loudml_py/scheduled_jobs.py
loudml_py/serializer.py
loudml_py/templates.py
loudml_py/transport.py
loudml_py/utils.py
loudml_py/wave.py
loudml_py/connection/__init__.py
loudml_py/connection/base.py
loudml_py/connection/http_requests.py
loudml_py/connection/http_urllib3.py
loudml_py/connection/pooling.py
loudml_python-1.6.2.dist-info/LICENSE
loudml_python-1.6.2.dist-info/METADATA
loudml_python-1.6.2.dist-info/WHEEL
loudml_python-1.6.2.dist-info/entry_points.txt
loudml_python-1.6.2.dist-info/top_level.txt
loudml_python-1.6.2.dist-info/RECORD
