Metadata-Version: 2.1
Name: loudml-python
Version: 1.6.2
Summary: Loud ML Python API Client
Home-page: https://github.com/loudml/loudml-python
Author: Loud ML
Author-email: support@loudml.io
License: MIT
Platform: UNKNOWN
Classifier: Development Status :: 4 - Beta
Classifier: Intended Audience :: Developers
Classifier: Operating System :: OS Independent
Classifier: License :: OSI Approved :: MIT License
Classifier: Programming Language :: Python :: 2
Classifier: Programming Language :: Python :: 2.7
Classifier: Programming Language :: Python :: 3
Classifier: Programming Language :: Python :: 3.2
Classifier: Programming Language :: Python :: 3.3
Classifier: Programming Language :: Python :: 3.4
Classifier: Programming Language :: Python :: 3.5
Classifier: Programming Language :: Python :: 3.6
Classifier: Programming Language :: Python :: 3.7
Requires-Python: >=2.7, !=3.0.*, !=3.1.*
Requires-Dist: requests (>=2.14.0)
Requires-Dist: pyyaml (==5.1.2)
Requires-Dist: tqdm (>=4.35.0)
Requires-Dist: pytz (>=2019.2)
Requires-Dist: dateutils (>=0.6.6)
Requires-Dist: certifi
Provides-Extra: test
Requires-Dist: mock ; extra == 'test'
